README.md
setup.cfg
setup.py
pyker/__init__.py
pyker/card.py
pyker/constants.py
pyker/hand.py
pyker/version.py
pyker.egg-info/PKG-INFO
pyker.egg-info/SOURCES.txt
pyker.egg-info/dependency_links.txt
pyker.egg-info/not-zip-safe
pyker.egg-info/top_level.txt
sample/__init__.py